vatman/__init__.py
vatman/drawing/__init__.py
vatman/drawing/captions_overlay.py
vatman/drawing/grid.py
vatman/drawing/labels.py
vatman/drawing/text_utils.py
vatman/drawing/title.py
vatman/grid_builder.py
vatman-0.0.4.dist-info/LICENSE
vatman-0.0.4.dist-info/METADATA
vatman-0.0.4.dist-info/WHEEL
vatman-0.0.4.dist-info/RECORD
