Metadata-Version: 2.3
Name: vatman
Version: 0.0.4
Summary: A small utility for drawing image boards
License: MIT
Author: Vadim Fedorov
Author-email: vadim.ai.lab@gmail.com
Requires-Python: >=3.10,<4.0
Classifier: Intended Audience :: Developers
Classifier: Intended Audience :: Science/Research
Classifier: License :: OSI Approved :: MIT License
Classifier: Programming Language :: Python :: 3
Classifier: Programming Language :: Python :: 3.10
Classifier: Programming Language :: Python :: 3.11
Classifier: Programming Language :: Python :: 3.12
Classifier: Programming Language :: Python :: 3.13
Classifier: Topic :: Scientific/Engineering :: Image Processing
Classifier: Topic :: Utilities
Requires-Dist: pillow (>=11.0.0)
Project-URL: Repository, https://github.com/Coderik/vatman
